setup.py
astronomer/__init__.py
astronomer/cli.py
astronomer/core.py
astronomer/writers.py
astronomer.egg-info/PKG-INFO
astronomer.egg-info/SOURCES.txt
astronomer.egg-info/dependency_links.txt
astronomer.egg-info/entry_points.txt
astronomer.egg-info/namespace_packages.txt
astronomer.egg-info/not-zip-safe
astronomer.egg-info/requires.txt
astronomer.egg-info/top_level.txt