Metadata-Version: 1.1
Name: astronomer
Version: 0.0.0
Summary: Fetch information about the users who've starred a given GitHub repository.
Home-page: http://github.com/jsvine/astronomer/
Author: Jeremy Singer-Vine
Author-email: jsvine@gmail.com
License: MIT
Keywords: github stars starred stargazers
Platform: UNKNOWN
Classifier: Development Status :: 3 - Alpha
Classifier: Intended Audience :: Developers
Classifier: License :: OSI Approved :: MIT License
Classifier: Operating System :: OS Independent
Classifier: Programming Language :: Python :: 2.6
Classifier: Programming Language :: Python :: 2.7
Classifier: Programming Language :: Python :: 3.3
